{
  "created": "2026-05-20T06:36:14.000Z",
  "creator": {
    "email": "myhanno-bot@city-tecoli.iam.gserviceaccount.com"
  },
  "description": "Automated translation (refer to source for accuracy)\n\nThe convenience store service for issuing tax (non-taxable) and income certificates will be temporarily suspended from May 31 to June 2, 2026 (Reiwa 8) for system maintenance. Service resumes on June 3, 2026 (Reiwa 8).\n\nIf you need a certificate during the suspension period, use one of these locations:\n\n【Hanno City Hall and District Administrative Centers】 9:00 AM – 4:30 PM (except Fujimi District Administrative Center)\n\n【Hanno Station Service Counter】 9:00 AM – 5:00 PM (same-day tax certificate issuance: 9:00 AM – 4:30 PM)\n\nAll other convenience store services remain available as usual.\n\nSource (Japanese): https://www.city.hanno.lg.jp/soshikikarasagasu/sogoseisakubu/johosystem/13166.html",
  "end": {
    "date": "2026-05-16"
  },
  "eventType": "default",
  "htmlLink": "https://www.google.com/calendar/event?eid=X2R0cG1ncWJpYzVwbWFiOWg2Y29qY2RpMGQxZ21zcmpmNXBobWl0M3A1cHE2YW9yZmRoa2lzb3JmZGsgYjZmMzZlMTk3NTFjMDVjY2U5OWZhMDA4MjhlNDI5ZjQwZjZkYjEwMGUyZGJlNDQyYmMyNjIyYTI1ZGE5NzMxNkBn",
  "iCalUID": "oshirase-13166@hanno.city.tecoli.com",
  "id": "_dtpmgqbic5pmab9h6cojcdi0d1gmsrjf5phmit3p5pq6aorfdhkisorfdk",
  "kind": "calendar#event",
  "organizer": {
    "displayName": "飯能市政（EN）",
    "email": "b6f36e19751c05cce99fa00828e429f40f6db100e2dbe442bc2622a25da97316@group.calendar.google.com",
    "self": true
  },
  "reminders": {
    "useDefault": false
  },
  "sequence": 0,
  "source": {
    "title": "www.city.hanno.lg.jp",
    "url": "https://www.city.hanno.lg.jp/soshikikarasagasu/sogoseisakubu/johosystem/13166.html"
  },
  "start": {
    "date": "2026-05-15"
  },
  "status": "confirmed",
  "summary": "ℹ️ Convenience store service for tax and income certificates suspended",
  "updated": "2026-05-22T05:38:36.697Z"
}