{
  "created": "2026-05-20T07:26:24.000Z",
  "creator": {
    "displayName": "Kaz Utashiro",
    "email": "kaz@utashiro.com"
  },
  "description": "### v1.20.1 修正\n- **イベント詳細をスクロールしているとき「離して更新」が誤発火していたのを修正** — モーダルを開いている間は自前 pull-to-refresh を発動しないように\n- **個人カレンダー (iCal URL) 取得時の起動エラーを修正** — v1.19.0 のレイアウト変更以降ずっと壊れていた regression\n- **英語版カレンダーなど「初期 OFF のカレンダー」をトグルしてもリロードで消えていたのを修正** — 設定を端末側 (localStorage) で保持するようにして、ネットワーク遅延に左右されないように\n\n### v1.20.0 イベントカレンダー\n- **「Myはんのう」と「飯能市政」の英語版カレンダーを追加** — 設定パネルから購読 ON にすると英語表記のイベントが表示されます (デフォルトはオフ)\n- **購読設定モデルを刷新** — 「デフォルト ON のカレンダーはオフにしたものだけ記録」「デフォルト OFF のカレンダーはオンにしたものだけ記録」の非対称管理に。第三者カレンダーや言語別カレンダーが正しい初期状態で出るようになりました\n\n### v1.19.2 バス\n- **トップで別日を選んでから「バスに乗る/帰る」を開くと、その日の時刻表が直接見えます**\n- **バスページにも前日/翌日ボタン + 日付クリックでカレンダーが付きました**\n- **時刻表の「あと X 分後」を切り捨て表示に** (1分未満は「1分未満」)\n- **途中停留所の時刻が等幅で揃って読みやすく**\n- **当日でない日のバス時刻表ではカウントダウンを出さず、途中停留所などの情報だけ表示**\n\n### v1.19.2 ゴミ収集\n- **当日午後 (12時以降) と過去日のゴミ欄は閉じた状態に** (朝のゴミ出し用途以外は畳んで邪魔にならないように)\n- **明日以降のゴミ欄は開きっぱなし** (一度閉じればその日の選択で記憶)\n\n### v1.19.2 細かい改善\n- 詳細リンクのマークが市長ブログのマークと衝突していたのを別アイコン (外部リンク矢印) に変更\n\n### v1.19.1 大きな変更\n- **トップページが「任意の日付」に対応** — 翌日/前日に切り替えるだけだったのが、画面全体を任意の日に切替えられるように。\n  - 大日付の両側に ◀️ ▶️ のボタンで前日/翌日\n  - 大日付をタップ → カレンダー で任意の日に飛べる\n  - 「明日」「N日後」等の 反転バッジ をタップ → いつでも 今日 に戻る\n  - 過去の天気も表示できます (数十年前まで)\n  - 当日でない日付は URL (?date=YYYY-MM-DD) で共有・ブックマーク可能\n\n### v1.19.1 朝のゴミ出し\n- 時計 は「今日のゴミ収集がある日」だけ、ピクトグラムの上に大きく表示します。寝起きで眼鏡がなくても時間がチェックできます。\n\n### v1.19.1 暦の見やすさ\n- 「土曜」全体を青、「日曜」と「祝日」全体を赤、で見やすく\n- 祝日名 (例: 憲法記念日 / みどりの日) は赤太字で暦帯に表示",
  "end": {
    "date": "2026-05-22"
  },
  "eventType": "default",
  "htmlLink": "https://www.google.com/calendar/event?eid=bGo0cWEzN290bWIycTVzMjYxZm5uMzhxN3MgMjA1NDAzYzk3MWRjNWVmMjFlZmQ4MWMxZDUzODQ5Y2FkZmQ5MDFiNzVjNzdkODg5NTVkOTYwMGY0NWYyYTAxM0Bn",
  "iCalUID": "lj4qa37otmb2q5s261fnn38q7s@google.com",
  "id": "lj4qa37otmb2q5s261fnn38q7s",
  "kind": "calendar#event",
  "organizer": {
    "displayName": "Myはんのう",
    "email": "205403c971dc5ef21efd81c1d53849cadfd901b75c77d88955d9600f45f2a013@group.calendar.google.com",
    "self": true
  },
  "reminders": {
    "useDefault": false
  },
  "sequence": 0,
  "start": {
    "date": "2026-05-20"
  },
  "status": "confirmed",
  "summary": "Myはんのう v1.20.1",
  "updated": "2026-05-22T03:31:02.148Z"
}