{
  "created": "2026-06-15T20:53:08.000Z",
  "creator": {
    "email": "myhanno-bot@city-tecoli.iam.gserviceaccount.com"
  },
  "description": "🆕 新着掲載 (公開日: 2026-06-15)\n\nAI による要約 (正確な情報は元記事をご確認ください)\n\n6月12日の雹による被災証明書発行。住家以外の構造物（店舗、倉庫、カーポート、門扉など）、車両、家財などが被災した事実を証明する書類です。\n\n申請に必要なもの：被災証明書交付申請書（所定様式に記入・捺印）、被災状況が確認できるプリント写真（必須）、本人確認書類（運転免許証、個人番号カードなど）。所有者本人または同居者以外が申請する場合は委任状も必要です。\n\n提出先は防災危機管理課（本庁舎別館1階）。受付は平日のみ9:00～16:30。電話042-973-2723。\n\n注意：発行は災害発生後おおむね1か月以内の状況をもとに証明。修繕完了後の申請など被災状況が確認できない場合は発行できない場合があります。被災箇所の写真は必ず撮影してください。\n\n飯能市公式サイト 新着情報: https://www.city.hanno.lg.jp/emergency/13705.html",
  "end": {
    "date": "2026-06-17"
  },
  "eventType": "default",
  "htmlLink": "https://www.google.com/calendar/event?eid=X2R0cG1ncWJpYzVwbWFiOWg2Y3JqMGQ5ZGNjcDM0cDM1NjkwNmdvYmVkcG5pc29yOWVoc2lzdDM1Y2RubW9xOWVjZG5tcSA2NzQ1OTE0YjI0MzIzMTEyYTE1ZjQzZGMyMGIzYTBmNGE0ODE3YWZkODAwYzhkMTY4N2QwYmYwYjdmODkwYzYxQGc",
  "iCalUID": "oshirase-13705-c22de2@hanno.city.tecoli.com",
  "id": "_dtpmgqbic5pmab9h6crj0d9dccp34p356906gobedpnisor9ehsist35cdnmoq9ecdnmq",
  "kind": "calendar#event",
  "organizer": {
    "displayName": "飯能市役所",
    "email": "6745914b24323112a15f43dc20b3a0f4a4817afd800c8d1687d0bf0b7f890c61@group.calendar.google.com",
    "self": true
  },
  "reminders": {
    "useDefault": false
  },
  "sequence": 0,
  "source": {
    "title": "www.city.hanno.lg.jp",
    "url": "https://www.city.hanno.lg.jp/emergency/13705.html"
  },
  "start": {
    "date": "2026-06-16"
  },
  "status": "confirmed",
  "summary": "ℹ️ 6月12日の雹(ひょう)の被害等による被災証明書の発行について",
  "updated": "2026-06-15T20:53:08.688Z"
}