{
  "created": "2026-05-17T23:37:38.000Z",
  "creator": {
    "email": "myhanno-bot@city-tecoli.iam.gserviceaccount.com"
  },
  "description": "AI による要約 (正確な情報は元記事をご確認ください)\n\n有効容量が10立方メートルを超える貯水槽（受水槽）を有する施設は、水道法に基づき「簡易専用水道」として適切な維持管理が義務付けられています。\n\n【定期的に実施する事項】\n・貯水槽（受水槽）の清掃：1年に1回以上\n・水質検査：1年に1回、登録検査機関にて実施\n\n設置者及び管理者の皆様は、浄水場でつくられた安全な水を各家庭へ適切に供給するため、貯水槽水道の衛生管理に努めてください。\n\n有効容量10立方メートル以下の小規模貯水槽水道の場合でも、簡易専用水道と同様の管理を行うよう努めてください。\n\n清掃や水質検査等を行った場合の水道工務課への報告は不要です。\n\n飯能市公式サイト 新着情報: https://www.city.hanno.lg.jp/soshikikarasagasu/jogesuidobu/suidokomuka/13444.html",
  "end": {
    "date": "2026-04-16"
  },
  "eventType": "default",
  "htmlLink": "https://www.google.com/calendar/event?eid=X2R0cG1ncWJpYzVwbWFiOWg2Y3EzOGQyMGQxZ21zcmpmNXBobWl0M3A1cHE2YW9yZmRoa2lzb3JmZGsgNjc0NTkxNGIyNDMyMzExMmExNWY0M2RjMjBiM2EwZjRhNDgxN2FmZDgwMGM4ZDE2ODdkMGJmMGI3Zjg5MGM2MUBn",
  "iCalUID": "oshirase-13444@hanno.city.tecoli.com",
  "id": "_dtpmgqbic5pmab9h6cq38d20d1gmsrjf5phmit3p5pq6aorfdhkisorfdk",
  "kind": "calendar#event",
  "organizer": {
    "displayName": "飯能市政",
    "email": "6745914b24323112a15f43dc20b3a0f4a4817afd800c8d1687d0bf0b7f890c61@group.calendar.google.com",
    "self": true
  },
  "reminders": {
    "useDefault": false
  },
  "sequence": 0,
  "source": {
    "title": "www.city.hanno.lg.jp",
    "url": "https://www.city.hanno.lg.jp/soshikikarasagasu/jogesuidobu/suidokomuka/13444.html"
  },
  "start": {
    "date": "2026-04-15"
  },
  "status": "confirmed",
  "summary": "ℹ️ 貯水槽水道（受水槽）の適正な管理について",
  "updated": "2026-05-22T07:20:58.309Z"
}